{
  "data": {
    "article": {},
    "attachments": {},
    "author_id": "1642270015851474944",
    "conversation_id": "2026697437986123933",
    "created_at": "2026-02-25T18:06:31.000Z",
    "edit_controls": {
      "editable_until": "2026-02-25T19:06:31.000Z",
      "edits_remaining": 5,
      "is_edit_eligible": false
    },
    "edit_history_tweet_ids": [
      "2026720479290208581"
    ],
    "entities": {
      "mentions": [
        {
          "end": 10,
          "id": "2019100298808291333",
          "start": 0,
          "username": "YuwenT233"
        },
        {
          "end": 19,
          "id": "1512976991976402949",
          "start": 11,
          "username": "bghtnya"
        }
      ]
    },
    "geo": {},
    "id": "2026720479290208581",
    "in_reply_to_user_id": "2019100298808291333",
    "lang": "zh",
    "note_tweet": {
      "entities": {}
    },
    "possibly_sensitive": false,
    "public_metrics": {
      "bookmark_count": 0,
      "impression_count": 0,
      "like_count": 0,
      "quote_count": 0,
      "reply_count": 0,
      "retweet_count": 0
    },
    "referenced_tweets": [
      {
        "id": "2026697437986123933",
        "type": "replied_to"
      }
    ],
    "reply_settings": "everyone",
    "text": "@YuwenT233 @bghtnya 都是抖音上那个人给画的？）"
  },
  "includes": {
    "media": [
      {
        "height": 1176,
        "media_key": "3_2026697431904399360",
        "public_metrics": {},
        "type": "photo",
        "url": "https://pbs.twimg.com/media/HCBGk4_bsAAl92Q.jpg",
        "width": 1176
      },
      {
        "height": 1083,
        "media_key": "3_2026697431895986176",
        "public_metrics": {},
        "type": "photo",
        "url": "https://pbs.twimg.com/media/HCBGk49bUAAi3Dj.jpg",
        "width": 1118
      }
    ],
    "tweets": [
      {
        "article": {},
        "attachments": {},
        "author_id": "1642270015851474944",
        "conversation_id": "2026697437986123933",
        "created_at": "2026-02-25T18:06:31.000Z",
        "edit_controls": {
          "editable_until": "2026-02-25T19:06:31.000Z",
          "edits_remaining": 5,
          "is_edit_eligible": false
        },
        "edit_history_tweet_ids": [
          "2026720479290208581"
        ],
        "entities": {
          "mentions": [
            {
              "end": 10,
              "id": "2019100298808291333",
              "start": 0,
              "username": "YuwenT233"
            },
            {
              "end": 19,
              "id": "1512976991976402949",
              "start": 11,
              "username": "bghtnya"
            }
          ]
        },
        "geo": {},
        "id": "2026720479290208581",
        "in_reply_to_user_id": "2019100298808291333",
        "lang": "zh",
        "note_tweet": {
          "entities": {}
        },
        "possibly_sensitive": false,
        "public_metrics": {
          "bookmark_count": 0,
          "impression_count": 0,
          "like_count": 0,
          "quote_count": 0,
          "reply_count": 0,
          "retweet_count": 0
        },
        "referenced_tweets": [
          {
            "id": "2026697437986123933",
            "type": "replied_to"
          }
        ],
        "reply_settings": "everyone",
        "text": "@YuwenT233 @bghtnya 都是抖音上那个人给画的？）"
      },
      {
        "article": {},
        "attachments": {
          "media_keys": [
            "3_2026697431904399360",
            "3_2026697431895986176"
          ]
        },
        "author_id": "2019100298808291333",
        "conversation_id": "2026697437986123933",
        "created_at": "2026-02-25T16:34:58.000Z",
        "edit_controls": {
          "editable_until": "2026-02-25T17:34:58.000Z",
          "edits_remaining": 5,
          "is_edit_eligible": true
        },
        "edit_history_tweet_ids": [
          "2026697437986123933"
        ],
        "entities": {
          "mentions": [
            {
              "end": 24,
              "id": "1512976991976402949",
              "start": 16,
              "username": "bghtnya"
            }
          ],
          "urls": [
            {
              "display_url": "pic.x.com/8PRg3Aqf0X",
              "end": 48,
              "expanded_url": "https://x.com/YuwenT233/status/2026697437986123933/photo/1",
              "media_key": "3_2026697431904399360",
              "start": 25,
              "url": "https://t.co/8PRg3Aqf0X"
            },
            {
              "display_url": "pic.x.com/8PRg3Aqf0X",
              "end": 48,
              "expanded_url": "https://x.com/YuwenT233/status/2026697437986123933/photo/1",
              "media_key": "3_2026697431895986176",
              "start": 25,
              "url": "https://t.co/8PRg3Aqf0X"
            }
          ]
        },
        "geo": {},
        "id": "2026697437986123933",
        "lang": "ja",
        "note_tweet": {
          "entities": {}
        },
        "possibly_sensitive": false,
        "public_metrics": {
          "bookmark_count": 1,
          "impression_count": 324,
          "like_count": 11,
          "quote_count": 0,
          "reply_count": 2,
          "retweet_count": 1
        },
        "reply_settings": "everyone",
        "text": "n55和唐毓文都有了 就差冰棍了@bghtnya https://t.co/8PRg3Aqf0X"
      }
    ],
    "users": [
      {
        "created_at": "2023-04-01T20:57:49.000Z",
        "description": "曾经的悲观阴郁币/咱叫吴水琦(网名吴雾晨)/梦想做一个北欧小姑娘/星宇比较大的小猫(bushi/喜欢一切可可爱爱的东西❤️/老公sama:@YeziLoveChen/对生活保持热爱/07大龄xyn🏳️‍⚧️/歡迎互fo！",
        "entities": {
          "description": {
            "mentions": [
              {
                "end": 82,
                "start": 69,
                "username": "YeziLoveChen"
              }
            ]
          }
        },
        "id": "1642270015851474944",
        "location": "Urumqi China",
        "name": "霧會散（霧晨晨）🌫️🏳️‍⚧️🍥",
        "pinned_tweet_id": "1825746968699875352",
        "profile_image_url": "https://pbs.twimg.com/profile_images/2025151367011336198/E3y_V5VL_normal.jpg",
        "protected": false,
        "public_metrics": {
          "followers_count": 379,
          "following_count": 404,
          "like_count": 521,
          "listed_count": 1,
          "media_count": 71,
          "tweet_count": 1145
        },
        "username": "NyaMist5",
        "verified": false
      },
      {
        "created_at": "2026-02-04T17:27:46.000Z",
        "description": "MTF｜🍥🏳️‍⚧️Hrt：2025.6.30｜持证含糖｜已净身😋😎｜需要10倍凝胶🍥找我对象@shaoxiancao1314 ｜观点过激🤔｜NSFW🥵｜墨尔本阻止自杀援助｜生日1019｜ENFP｜可能是最著名的反跨个人😰｜swich｜TransLes？｜雷极端键政｜一般极少屏蔽｜",
        "entities": {
          "description": {
            "mentions": [
              {
                "end": 63,
                "start": 47,
                "username": "shaoxiancao1314"
              }
            ]
          },
          "url": {
            "urls": [
              {
                "display_url": "MTFLEVEL.COM",
                "end": 23,
                "expanded_url": "http://MTFLEVEL.COM",
                "start": 0,
                "url": "https://t.co/UTbB3jsAQl"
              }
            ]
          }
        },
        "id": "2019100298808291333",
        "name": "唐毓文",
        "pinned_tweet_id": "2026425274393595949",
        "profile_image_url": "https://pbs.twimg.com/profile_images/2020000255790702592/OlSCtUnx_normal.jpg",
        "protected": false,
        "public_metrics": {
          "followers_count": 1558,
          "following_count": 69,
          "like_count": 162,
          "listed_count": 1,
          "media_count": 176,
          "tweet_count": 1289
        },
        "url": "https://t.co/UTbB3jsAQl",
        "username": "YuwenT233",
        "verified": true
      },
      {
        "created_at": "2022-04-10T02:13:28.000Z",
        "description": "📖🖥 大一计算机 / 🗺️📍 坐标北上待定 / 🍰1989.06.04 /  🧊🔥 冰棍必须是烫的！/  🍥 断续含糖  / 🏳‍⚧🏳️‍🌈  MTFTX.TransLes / 🦋 INFP-A  /  🏴🚩 Ⓐ☭ 政治立场偏左下   /   🌊 涌江入河水渠辟，润滋沃土生机荣",
        "entities": {
          "url": {
            "urls": [
              {
                "display_url": "mfuns.net/member/4328",
                "end": 23,
                "expanded_url": "https://mfuns.net/member/4328",
                "start": 0,
                "url": "https://t.co/o4J1P8mtmq"
              }
            ]
          }
        },
        "id": "1512976991976402949",
        "location": "https://github.com/bghtnya",
        "name": "冰棍好烫喵 🍥🧊🍔🍟🍜🍣🍙🍧🍮🍩☕️💊🤤",
        "profile_image_url": "https://pbs.twimg.com/profile_images/2024810573549219840/icSpV9Yg_normal.jpg",
        "protected": false,
        "public_metrics": {
          "followers_count": 9029,
          "following_count": 2082,
          "like_count": 174318,
          "listed_count": 18,
          "media_count": 3781,
          "tweet_count": 46130
        },
        "url": "https://t.co/o4J1P8mtmq",
        "username": "bghtnya",
        "verified": true
      }
    ]
  }
}